.gitlab-ci.yml
MANIFEST.in
README.md
setup.cfg
setup.py
versioneer.py
bmlx_components/__init__.py
bmlx_components/_version.py
bmlx_components/custom_artifacts.py
bmlx_components/dependencies.py
bmlx_components.egg-info/PKG-INFO
bmlx_components.egg-info/SOURCES.txt
bmlx_components.egg-info/dependency_links.txt
bmlx_components.egg-info/namespace_packages.txt
bmlx_components.egg-info/not-zip-safe
bmlx_components.egg-info/requires.txt
bmlx_components.egg-info/top_level.txt
bmlx_components/fg_importer/__init__.py
bmlx_components/fg_importer/component.py
bmlx_components/fg_importer/driver.py
bmlx_components/importer_node/__init__.py
bmlx_components/importer_node/component.py
bmlx_components/importer_node/driver.py
bmlx_components/importer_node/import_checker.py
bmlx_components/importer_node/importer_test.py
bmlx_components/mlplat-protos/__init__.py
bmlx_components/mlplat-protos/mlplat/__init__.py
bmlx_components/mlplat-protos/mlplat/feature/__init__.py
bmlx_components/mlplat-protos/mlplat/feature/common_pb2.py
bmlx_components/mlplat-protos/mlplat/feature/example_pb2.py
bmlx_components/mlplat-protos/mlplat/feature/feature_pb2.py
bmlx_components/mlplat-protos/mlplat/feature/model_sample_pb2.py
bmlx_components/mlplat-protos/mlplat/feature/original_feature_pb2.py
bmlx_components/mlplat-protos/mlplat/feature/sample_pb2.py
bmlx_components/mlplat-protos/mlplat/feature/score_pb2.py
bmlx_components/model_cleaner/__init__.py
bmlx_components/model_cleaner/component.py
bmlx_components/model_cleaner/executor.py
bmlx_components/model_cleaner_v2/__init__.py
bmlx_components/model_cleaner_v2/component.py
bmlx_components/model_cleaner_v2/executor.py
bmlx_components/proto/__init__.py
bmlx_components/proto/model_pb2.py
bmlx_components/proto/schema_pb2.py
bmlx_components/rtp_pusher/__init__.py
bmlx_components/rtp_pusher/component.py
bmlx_components/rtp_pusher/executor.py
bmlx_components/rtp_pusher_v2/__init__.py
bmlx_components/rtp_pusher_v2/component.py
bmlx_components/rtp_pusher_v2/executor.py
bmlx_components/rtp_pusher_v2/resource_uploader.py
bmlx_components/sample_selector/__init__.py
bmlx_components/sample_selector/component.py
bmlx_components/sample_selector/driver.py
bmlx_components/sample_selector/driver_test.py
bmlx_components/sample_selector_v2/__init__.py
